Assignment_4/3/Registers.v
//Name: K Krishna Swaroop & Ameya Deshpande
//Roll no.:181CO125 & 181CO205
//Date:23/10/2019
//Question No.:3
//Program:Implements 32 bit register file
//        (writes(input en_write=1) and reads(en_write=0) to a 32 bit register 

module regfile(input clock,input reset, input [4:0] address,
               input en_write, input [31:0] idata,output [31:0] data);

// Register file storage
reg [31:0] registers[31:0];
reg [31:0] out_val;

// Read and write from register file
always @(posedge clock)
    if(!reset) begin
        if (en_write)
                registers[address] <= idata;
        else
                out_val <= registers[address];
    end

assign data = en_write ? 32'bx : out_val;

endmodule

`timescale 1ns / 1ps
module stimulus;
    reg clock;
    reg reset;
    reg [4:0] address;
    reg en_write;
    reg [31:0] idata;
    wire [31:0] data;

    regfile r1(
        .clock(clock),
        .reset(reset),
        .address(address),
        .en_write(en_write),
        .idata(idata),
        .data(data)
    );

    integer i;
 
	initial begin
	$dumpfile("regfile.vcd");
    $dumpvars(0,stimulus);
    reset = 0;
	#5 en_write=1; address=1; idata= 13456789;
	#5 en_write=0; address=1; 
    #10
	#5 en_write=1; address=8; idata= 45678;	
	#5 en_write=0; address=8; 
    #10	
    #5 en_write=1; address=1; idata=23456787;
	#5 en_write=0; address=1; 
    #10
    #5 en_write=1; address=15; idata= 876545122;
	#5 en_write=0; address=15; 
    #10
	#5 en_write=1; address=22; idata= 76543235678;	
	#5 en_write=0; address=22; 	
    #10
    #5 en_write=1; address=31; idata =134567;
	#5 en_write=0; address=31; 
    #10
    #5 en_write=1; address=22; idata= 1102983746;
	#5 en_write=0; address=22; 
    #10
	#5 en_write=1; address=18; idata= 45678;	
	#5 en_write=0; address=18; 	
    #5 en_write=1; address=13; idata =23456787;
	#5 en_write=0; address=13; 	
    #10;
    end  
 
	initial begin
	clock = 0;
	for ( i =0; i <=10; i= i+1)
	#5 clock = ~clock;
    end  
 
 
	initial begin
		$monitor("clock=%d,reset=%d,address=%d,en_write=%d,idata=%d,data=%d \n",clock,reset,address,en_write,idata,data);
	end

endmodule

Assignment_4/3/regfile.vcd
$date
	Wed Nov 13 16:20:01 2019
$end
$version
	Icarus Verilog
$end
$timescale
	1ps
$end
$scope module stimulus $end
$var wire 32 ! data [31:0] $end
$var reg 5 " address [4:0] $end
$var reg 1 # clock $end
$var reg 1 $ en_write $end
$var reg 32 % idata [31:0] $end
$var reg 1 & reset $end
$var integer 32 ' i [31:0] $end
$scope module r1 $end
$var wire 5 ( address [4:0] $end
$var wire 1 # clock $end
$var wire 1 $ en_write $end
$var wire 32 ) idata [31:0] $end
$var wire 1 & reset $end
$var wire 32 * data [31:0] $end
$var reg 32 + out_val [31:0] $end
$upscope $end
$upscope $end
$enddefinitions $end
#0
$dumpvars
bx +
bx *
bx )
bx (
b0 '
0&
bx %
x$
0#
bx "
bx !
$end
#5000
b1 '
1#
b110011010101010110010101 %
b110011010101010110010101 )
b1 "
b1 (
1$
#10000
b10 '
0#
0$
#15000
b110011010101010110010101 !
b110011010101010110010101 *
b110011010101010110010101 +
b11 '
1#
#20000
b100 '
0#
#25000
bx !
bx *
b101 '
1#
b1011001001101110 %
b1011001001101110 )
b1000 "
b1000 (
1$
#30000
b110011010101010110010101 !
b110011010101010110010101 *
b110 '
0#
0$
#35000
b1011001001101110 !
b1011001001101110 *
b1011001001101110 +
b111 '
1#
#40000
b1000 '
0#
#45000
bx !
bx *
b1001 '
1#
b1011001011110110000010011 %
b1011001011110110000010011 )
b1 "
b1 (
1$
#50000
b1011001001101110 !
b1011001001101110 *
b1010 '
0#
0$
#55000
b1011001011110110000010011 !
b1011001011110110000010011 *
b1011001011110110000010011 +
b1011 '
1#
#65000
bx !
bx *
b110100001111110000010001100010 %
b110100001111110000010001100010 )
b1111 "
b1111 (
1$
#70000
b1011001011110110000010011 !
b1011001011110110000010011 *
0$
#85000
bx !
bx *
b11010010010101010001011001011110 %
b11010010010101010001011001011110 )
b10110 "
b10110 (
1$
#90000
b1011001011110110000010011 !
b1011001011110110000010011 *
0$
#105000
bx !
bx *
b100000110110100111 %
b100000110110100111 )
b11111 "
b11111 (
1$
#110000
b1011001011110110000010011 !
b1011001011110110000010011 *
0$
#125000
bx !
bx *
b1000001101111100011001001000010 %
b1000001101111100011001001000010 )
b10110 "
b10110 (
1$
#130000
b1011001011110110000010011 !
b1011001011110110000010011 *
0$
#145000
bx !
bx *
b1011001001101110 %
b1011001001101110 )
b10010 "
b10010 (
1$
#150000
b1011001011110110000010011 !
b1011001011110110000010011 *
0$
#155000
bx !
bx *
b1011001011110110000010011 %
b1011001011110110000010011 )
b1101 "
b1101 (
1$
#160000
b1011001011110110000010011 !
b1011001011110110000010011 *
0$
