Assignment_4/2/dff.v
module dff(D, clk, Q, r);
input D, clk, r;
output reg Q;
always @ (posedge clk)
begin
Q<=D;
if(r)
Q<=1'b0;
end
endmodule

Assignment_4/2/regi.v
module regi(D, clk, Q, r);
input [31:0] D;
input clk, r;
output [31:0] Q;
dff d0(D[0], clk, Q[0], r);
dff d1(D[1], clk, Q[1], r);
dff d2(D[2], clk, Q[2], r);
dff d3(D[3], clk, Q[3], r);
dff d4(D[4], clk, Q[4], r);
dff d5(D[5], clk, Q[5], r);
dff d6(D[6], clk, Q[6], r);
dff d7(D[7], clk, Q[7], r);
dff d8(D[8], clk, Q[8], r);
dff d9(D[9], clk, Q[9], r);
dff d10(D[10], clk, Q[10], r);
dff d11(D[11], clk, Q[11], r);
dff d12(D[12], clk, Q[12], r);
dff d13(D[13], clk, Q[13], r);
dff d14(D[14], clk, Q[14], r);
dff d15(D[15], clk, Q[15], r);
dff d16(D[16], clk, Q[16], r);
dff d17(D[17], clk, Q[17], r);
dff d18(D[18], clk, Q[18], r);
dff d19(D[19], clk, Q[19], r);
dff d20(D[20], clk, Q[20], r);
dff d21(D[21], clk, Q[21], r);
dff d22(D[22], clk, Q[22], r);
dff d23(D[23], clk, Q[23], r);
dff d24(D[24], clk, Q[24], r);
dff d25(D[25], clk, Q[25], r);
dff d26(D[26], clk, Q[26], r);
dff d27(D[27], clk, Q[27], r);
dff d28(D[28], clk, Q[28], r);
dff d29(D[29], clk, Q[29], r);
dff d30(D[30], clk, Q[30], r);
dff d31(D[31], clk, Q[31], r);
endmodule

Assignment_4/2/regi_TB.v
module regi_TB();
reg [31:0] D;
reg En, r;
wire [31:0] Q;
regi R1(D, En, Q, r);
initial
begin
En = 0;
forever
#5 En = ~En;
end
initial begin
D = 0;
r = 0;
repeat (7) begin
#5 r=~r; D = $random;
#6 r=~r; D = $random;
#7 r=~r; D = $random;
end
#5 $finish;
end
initial
begin
$dumpfile("regi.vcd");
$dumpvars(0, regi_TB);
end
always @ (Q) begin
$display($time, ". Pass. D = %b, Q = %b, r: %b", D, Q, r);
end
endmodule

Assignment_4/2/regi.vcd
$date
	Fri Oct 25 14:47:35 2019
$end
$version
	Icarus Verilog
$end
$timescale
	1s
$end
$scope module regi_TB $end
$var wire 32 ! Q [31:0] $end
$var reg 32 " D [31:0] $end
$var reg 1 # En $end
$var reg 1 $ r $end
$scope module R1 $end
$var wire 32 % D [31:0] $end
$var wire 32 & Q [31:0] $end
$var wire 1 ' clk $end
$var wire 1 ( r $end
$scope module d0 $end
$var wire 1 ) D $end
$var wire 1 ' clk $end
$var wire 1 ( r $end
$var reg 1 * Q $end
$upscope $end
$scope module d1 $end
$var wire 1 + D $end
$var wire 1 ' clk $end
$var wire 1 ( r $end
$var reg 1 , Q $end
$upscope $end
$scope module d2 $end
$var wire 1 - D $end
$var wire 1 ' clk $end
$var wire 1 ( r $end
$var reg 1 . Q $end
$upscope $end
$scope module d3 $end
$var wire 1 / D $end
$var wire 1 ' clk $end
$var wire 1 ( r $end
$var reg 1 0 Q $end
$upscope $end
$scope module d4 $end
$var wire 1 1 D $end
$var wire 1 ' clk $end
$var wire 1 ( r $end
$var reg 1 2 Q $end
$upscope $end
$scope module d5 $end
$var wire 1 3 D $end
$var wire 1 ' clk $end
$var wire 1 ( r $end
$var reg 1 4 Q $end
$upscope $end
$scope module d6 $end
$var wire 1 5 D $end
$var wire 1 ' clk $end
$var wire 1 ( r $end
$var reg 1 6 Q $end
$upscope $end
$scope module d7 $end
$var wire 1 7 D $end
$var wire 1 ' clk $end
$var wire 1 ( r $end
$var reg 1 8 Q $end
$upscope $end
$scope module d8 $end
$var wire 1 9 D $end
$var wire 1 ' clk $end
$var wire 1 ( r $end
$var reg 1 : Q $end
$upscope $end
$scope module d9 $end
$var wire 1 ; D $end
$var wire 1 ' clk $end
$var wire 1 ( r $end
$var reg 1 < Q $end
$upscope $end
$scope module d10 $end
$var wire 1 = D $end
$var wire 1 ' clk $end
$var wire 1 ( r $end
$var reg 1 > Q $end
$upscope $end
$scope module d11 $end
$var wire 1 ? D $end
$var wire 1 ' clk $end
$var wire 1 ( r $end
$var reg 1 @ Q $end
$upscope $end
$scope module d12 $end
$var wire 1 A D $end
$var wire 1 ' clk $end
$var wire 1 ( r $end
$var reg 1 B Q $end
$upscope $end
$scope module d13 $end
$var wire 1 C D $end
$var wire 1 ' clk $end
$var wire 1 ( r $end
$var reg 1 D Q $end
$upscope $end
$scope module d14 $end
$var wire 1 E D $end
$var wire 1 ' clk $end
$var wire 1 ( r $end
$var reg 1 F Q $end
$upscope $end
$scope module d15 $end
$var wire 1 G D $end
$var wire 1 ' clk $end
$var wire 1 ( r $end
$var reg 1 H Q $end
$upscope $end
$scope module d16 $end
$var wire 1 I D $end
$var wire 1 ' clk $end
$var wire 1 ( r $end
$var reg 1 J Q $end
$upscope $end
$scope module d17 $end
$var wire 1 K D $end
$var wire 1 ' clk $end
$var wire 1 ( r $end
$var reg 1 L Q $end
$upscope $end
$scope module d18 $end
$var wire 1 M D $end
$var wire 1 ' clk $end
$var wire 1 ( r $end
$var reg 1 N Q $end
$upscope $end
$scope module d19 $end
$var wire 1 O D $end
$var wire 1 ' clk $end
$var wire 1 ( r $end
$var reg 1 P Q $end
$upscope $end
$scope module d20 $end
$var wire 1 Q D $end
$var wire 1 ' clk $end
$var wire 1 ( r $end
$var reg 1 R Q $end
$upscope $end
$scope module d21 $end
$var wire 1 S D $end
$var wire 1 ' clk $end
$var wire 1 ( r $end
$var reg 1 T Q $end
$upscope $end
$scope module d22 $end
$var wire 1 U D $end
$var wire 1 ' clk $end
$var wire 1 ( r $end
$var reg 1 V Q $end
$upscope $end
$scope module d23 $end
$var wire 1 W D $end
$var wire 1 ' clk $end
$var wire 1 ( r $end
$var reg 1 X Q $end
$upscope $end
$scope module d24 $end
$var wire 1 Y D $end
$var wire 1 ' clk $end
$var wire 1 ( r $end
$var reg 1 Z Q $end
$upscope $end
$scope module d25 $end
$var wire 1 [ D $end
$var wire 1 ' clk $end
$var wire 1 ( r $end
$var reg 1 \ Q $end
$upscope $end
$scope module d26 $end
$var wire 1 ] D $end
$var wire 1 ' clk $end
$var wire 1 ( r $end
$var reg 1 ^ Q $end
$upscope $end
$scope module d27 $end
$var wire 1 _ D $end
$var wire 1 ' clk $end
$var wire 1 ( r $end
$var reg 1 ` Q $end
$upscope $end
$scope module d28 $end
$var wire 1 a D $end
$var wire 1 ' clk $end
$var wire 1 ( r $end
$var reg 1 b Q $end
$upscope $end
$scope module d29 $end
$var wire 1 c D $end
$var wire 1 ' clk $end
$var wire 1 ( r $end
$var reg 1 d Q $end
$upscope $end
$scope module d30 $end
$var wire 1 e D $end
$var wire 1 ' clk $end
$var wire 1 ( r $end
$var reg 1 f Q $end
$upscope $end
$scope module d31 $end
$var wire 1 g D $end
$var wire 1 ' clk $end
$var wire 1 ( r $end
$var reg 1 h Q $end
$upscope $end
$upscope $end
$upscope $end
$enddefinitions $end
#0
$dumpvars
xh
0g
xf
0e
xd
0c
xb
0a
x`
0_
x^
0]
x\
0[
xZ
0Y
xX
0W
xV
0U
xT
0S
xR
0Q
xP
0O
xN
0M
xL
0K
xJ
0I
xH
0G
xF
0E
xD
0C
xB
0A
x@
0?
x>
0=
x<
0;
x:
09
x8
07
x6
05
x4
03
x2
01
x0
0/
x.
0-
x,
0+
x*
0)
0(
0'
bx &
b0 %
0$
0#
b0 "
bx !
$end
#5
0*
0,
0.
00
02
04
06
08
0:
0<
0>
0@
0B
0D
0F
0H
0J
0L
0N
0P
0R
0T
0V
0X
0Z
0\
0^
0`
0b
0d
0f
0h
b0 !
b0 &
1-
13
19
1=
1A
1C
1I
1M
1Q
1[
1a
b10010000101010011010100100100 "
b10010000101010011010100100100 %
1$
1(
1#
1'
#10
0#
0'
#11
1)
0-
03
17
09
1;
1?
0C
1E
0M
1O
0Q
1W
0[
0a
1e
b11000000100010010101111010000001 "
b11000000100010010101111010000001 %
0$
0(
#15
1f
1X
1P
1J
1F
1B
1@
1>
1<
18
1*
b1000000100010010101111010000001 !
b1000000100010010101111010000001 &
1#
1'
#18
1/
07
0?
1G
0I
1M
0O
1]
0e
b10000100100001001101011000001001 "
b10000100100001001101011000001001 %
1$
1(
#20
0#
0'
#23
1+
0/
13
15
0G
0M
1Q
1S
1U
1Y
0]
1a
1c
1g
b10110001111100000101011001100011 "
b10110001111100000101011001100011 %
0$
0(
#25
1,
14
16
08
0@
0J
0P
1R
1T
1V
1Z
1b
1d
0f
1h
b10110001111100000101011001100011 !
b10110001111100000101011001100011 &
1#
1'
#29
0+
1-
1/
03
05
19
0=
1?
1C
1I
1O
0U
0Y
1[
1]
0a
0c
b110101110010111101100001101 "
b110101110010111101100001101 %
1$
1(
#30
0#
0'
#35
0h
0d
0b
0^
0\
0Z
0X
0V
0T
0R
0P
0J
0F
0D
0B
0@
0>
0<
0:
06
04
00
0.
0,
0*
b0 !
b0 &
1#
1'
#36
17
0;
0C
0E
1G
1K
1M
0S
1U
1e
0g
b1000110110111111001100110001101 "
b1000110110111111001100110001101 %
0$
0(
#40
0#
0'
#41
0/
13
15
07
09
1=
0?
0A
0I
0M
0O
0Q
0]
1a
1c
0e
b10110010110000101000010001100101 "
b10110010110000101000010001100101 %
1$
1(
#45
0*
0.
04
06
0>
0H
0L
0V
0X
0\
0b
0d
b0 !
b0 &
1#
1'
#47
0)
1+
0-
11
03
05
1;
0=
1A
1E
0G
1I
1M
1Q
1S
0U
0W
1Y
0[
1_
0a
0c
1g
b10001001001101110101001000010010 "
b10001001001101110101001000010010 %
0$
0(
#50
0#
0'
#54
1)
0+
01
19
0A
1C
1G
0M
1U
1W
0Y
0_
b111100111110001100000001 "
b111100111110001100000001 %
1$
1(
#55
0h
0X
0V
0T
0R
0L
0J
0H
0F
0D
0<
0:
0*
b0 !
b0 &
1#
1'
#59
1-
1/
0;
1=
1?
0C
1M
0S
1[
1]
0g
b110110101111100110100001101 "
b110110101111100110100001101 %
0$
0(
#60
0#
0'
#65
0,
0.
02
04
06
0:
0B
0D
0F
0H
0J
0L
0T
0Z
0\
0`
0b
0d
0h
b0 !
b0 &
0)
1+
0/
11
13
15
0=
0?
1A
1C
0M
0Q
1S
0U
0W
1Y
0]
1_
1a
1c
1g
1#
1'
b111011001000111111000101110110 "
b111011001000111111000101110110 %
1$
1(
#70
0#
0'
#72
1)
0+
1/
05
1=
1?
0A
0C
0K
1M
1O
0S
1W
0Y
1]
0c
0g
b11110100011011100110100111101 "
b11110100011011100110100111101 %
0$
0(
#75
1b
1`
1^
1\
1X
1P
1N
1J
1H
1F
1@
1>
1:
14
12
10
1.
1*
b11110100011011100110100111101 !
b11110100011011100110100111101 &
1#
1'
#77
01
15
17
1;
0?
1A
0G
0I
0O
1Q
1U
0_
1c
1e
b1110110110101000101011111101101 "
b1110110110101000101011111101101 %
1$
1(
#80
0#
0'
#83
0)
03
05
1C
1G
1I
1O
0Q
1S
0U
0W
0a
0c
1g
b1000110001011011111011110001100 "
b1000110001011011111011110001100 %
0$
0(
#85
0*
02
04
18
1<
0@
1B
1D
1T
0X
0`
0b
1f
1h
b11000110001011011111011110001100 !
b11000110001011011111011110001100 &
1#
1'
#90
1)
0-
11
13
15
0;
0=
1?
0A
1Q
1U
1W
0[
1_
1a
1c
0#
0'
b1111100111111011110100111111001 "
b1111100111111011110100111111001 %
1$
1(
#95
1d
0^
1Z
1R
0P
1L
0H
0F
0B
0<
0:
16
00
1,
b11100011001101110010010011000110 !
b11100011001101110010010011000110 &
0)
1+
1-
0/
01
03
09
1=
0?
0E
0G
1K
0O
0U
0W
1Y
1[
0]
0_
0a
1#
1'
b11100011001101110010010011000110 "
b11100011001101110010010011000110 %
0$
0(
#100
0#
0'
#101
1)
0+
0C
1G
1U
1W
0Y
b11100010111101111000010011000101 "
b11100010111101111000010011000101 %
1$
1(
#105
0*
0,
0.
06
08
0>
0D
0H
0J
0L
0N
0R
0T
0V
0X
0Z
0\
0d
0f
0h
b0 !
b0 &
1#
1'
#108
0)
1+
0-
1/
13
05
1;
0=
1A
1E
0M
0S
0U
0W
1Y
0[
1]
1a
0c
0g
b11010101000100111101001010101010 "
b11010101000100111101001010101010 %
0$
0(
#110
0#
0'
#113
1)
0+
1-
0/
15
19
1=
1C
1M
1O
0Q
1S
1W
0Y
1[
0]
1c
1g
b1110010101011111111011111100101 "
b1110010101011111111011111100101 %
1$
1(
#115
0h
0f
0d
0b
0\
0X
0T
0P
0N
0L
0J
0H
0F
0D
0B
0>
0<
0:
08
06
04
0.
0*
b0 !
b0 &
1#
1'
#119
1+
11
07
09
0=
0G
0I
0M
0O
1Q
0S
1U
1Y
1_
0e
0g
b10111011110100100111001001110111 "
b10111011110100100111001001110111 %
0$
0(
#120
0#
0'
#125
1*
1,
1.
12
14
16
1<
1B
1D
1F
1L
1R
1V
1X
1Z
1\
1`
1b
1d
b111011110100100111001001110111 !
b111011110100100111001001110111 &
1#
1'
#126
0)
0-
03
05
1=
0C
1G
1S
0U
0W
0[
0a
0c
1g
b10001001001100101101011000010010 "
b10001001001100101101011000010010 %
1$
1(
#130
0#
0'
